pytest_ai/__init__.py
pytest_ai/models.py
pytest_ai/test_generator.py
pytest_ai/prompts/__init__.py
pytest_ai/prompts/edge.py
pytest_ai/prompts/regular.py
pytest_ai/prompts/security.py
pytest_ai/utils/__init__.py
pytest_ai/utils/folders.py
pytest_ai/utils/model_integration.py
pytest_ai-0.2.0.dist-info/LICENSE
pytest_ai-0.2.0.dist-info/METADATA
pytest_ai-0.2.0.dist-info/WHEEL
pytest_ai-0.2.0.dist-info/top_level.txt
pytest_ai-0.2.0.dist-info/RECORD
